[
    {
      "pregunta": "¿En qué años ocurrió la Guerra del Golfo Pérsico?",
      "respuesta": "1990-1991"
    },
    {
      "pregunta": "¿Qué país invadió Kuwait en 1990?",
      "respuesta": "Irak"
    },
    {
      "pregunta": "¿Qué alegaba Saddam Hussein para justificar la invasión a Kuwait?",
      "respuesta": "Que el territorio siempre había pertenecido a Irak"
    },
    {
      "pregunta": "¿Qué día invadió Irak a Kuwait?",
      "respuesta": "2 de agosto de 1990"
    },
    {
      "pregunta": "¿Qué presidente lideró la coalición internacional contra Irak?",
      "respuesta": "George H. W. Bush"
    },
    {
      "pregunta": "¿Quién fue el presidente de Irak durante la guerra?",
      "respuesta": "Saddam Hussein"
    },
    {
      "pregunta": "¿Qué general estadounidense lideró las operaciones militares?",
      "respuesta": "Norman Schwarzkopf"
    },
    {
      "pregunta": "¿Quién era el Jefe del Estado Mayor Conjunto de EE.UU.?",
      "respuesta": "Colin Powell"
    },
    {
      "pregunta": "¿Qué operación movilizó tropas en Arabia Saudita?",
      "respuesta": "Operación Escudo del Desierto"
    },
    {
      "pregunta": "¿Cuándo comenzó la Operación Tormenta del Desierto?",
      "respuesta": "17 de enero de 1991"
    },
    {
      "pregunta": "¿Qué operación liberó Kuwait mediante una ofensiva terrestre?",
      "respuesta": "Operación Sable del Desierto"
    },
    {
      "pregunta": "¿En qué fecha comenzó la Operación Sable del Desierto?",
      "respuesta": "24 de febrero de 1991"
    },
    {
      "pregunta": "¿Cuánto tiempo tomó liberar Kuwait durante la ofensiva terrestre?",
      "respuesta": "Cuatro días"
    },
    {
      "pregunta": "¿Cuál fue una de las batallas más importantes de la ofensiva terrestre?",
      "respuesta": "Batalla de 73 Easting"
    },
    {
      "pregunta": "¿Qué avión furtivo fue clave en los bombardeos aéreos?",
      "respuesta": "F-117 Nighthawk"
    },
    {
      "pregunta": "¿Qué bombardero estratégico se usó en la guerra?",
      "respuesta": "B-52 Stratofortress"
    },
    {
      "pregunta": "¿Qué misil teledirigido fue utilizado por EE.UU.?",
      "respuesta": "Tomahawk"
    },
    {
      "pregunta": "¿Qué misil se utilizó para defensa antiaérea?",
      "respuesta": "Patriot"
    },
    {
      "pregunta": "¿Qué tanque fue el principal de la coalición?",
      "respuesta": "M1 Abrams"
    },
    {
      "pregunta": "¿Qué sistema ayudó en la navegación y precisión de ataques?",
      "respuesta": "GPS"
    },
    {
      "pregunta": "¿Qué país de Latinoamérica participó en la coalición?",
      "respuesta": "Argentina"
    },
    {
      "pregunta": "¿Qué fase naval comenzó en agosto de 1990?",
      "respuesta": "Bloqueo naval"
    },
    {
      "pregunta": "¿Qué tipo de operaciones se realizaron para proteger barcos comerciales?",
      "respuesta": "Protección de convoyes"
    },
    {
      "pregunta": "¿Qué se hizo en las aguas del Golfo tras la retirada iraquí?",
      "respuesta": "Desminado"
    },
    {
      "pregunta": "¿Qué tipo de conflicto fue la Guerra del Golfo según William Lind?",
      "respuesta": "Guerra de Tercera Generación"
    },
        {
          "pregunta": "¿Qué tipo de guerra describe William Lind para la Guerra del Golfo?",
          "respuesta": "Tercera Generación"
        },
        {
          "pregunta": "¿Qué conceptos clave definen una guerra de tercera generación?",
          "respuesta": "Velocidad, sigilo y sorpresa"
        },
        {
          "pregunta": "¿Qué país del Medio Oriente formó parte de la coalición y fue invadido?",
          "respuesta": "Kuwait"
        },
        {
          "pregunta": "¿Qué país europeo formó parte de la coalición y tiene capital en Londres?",
          "respuesta": "Reino Unido"
        },
        {
          "pregunta": "¿Qué fuerza se integró en operaciones conjuntas con Armada y Fuerza Terrestre?",
          "respuesta": "Fuerza Aérea"
        },
        {
          "pregunta": "¿Cómo se denominan las operaciones entre varios países?",
          "respuesta": "Operaciones combinadas"
        },
        {
          "pregunta": "¿Cuál fue el objetivo de las operaciones navales?",
          "respuesta": "Explotar el control del mar y proyectar el poder naval"
        },
        {
          "pregunta": "¿Qué objetivos incluye la estrategia naval?",
          "respuesta": "Fuerza Organizada, Posición Estratégica, Comunicaciones Marítimas"
        },
        {
          "pregunta": "¿Qué países garantes participaron en la coalición?",
          "respuesta": "EE.UU., Reino Unido, Francia, entre otros"
        },
        {
          "pregunta": "¿Cuál fue el propósito del bloqueo naval iniciado en agosto de 1990?",
          "respuesta": "Cortar suministro de armas y recursos a Irak"
        },
        {
          "pregunta": "¿Qué tipo de misiles fueron lanzados desde buques y submarinos?",
          "respuesta": "Tomahawk"
        },
        {
          "pregunta": "¿Qué se protegía al escoltar barcos comerciales en la campaña marítima?",
          "respuesta": "Tránsito seguro frente a ataques iraquíes"
        },
        {
          "pregunta": "¿Cuándo comenzaron los ataques iniciales de la campaña aérea?",
          "respuesta": "17 de enero de 1991"
        },
        {
          "pregunta": "¿Qué sistema usaron los F-4G Wild Weasel para neutralizar defensas?",
          "respuesta": "Misiles antirradar HARM"
        },
        {
          "pregunta": "¿Cuántas salidas realizó la aviación de la coalición?",
          "respuesta": "Más de 100.000"
        },
        {
          "pregunta": "¿Cuántas toneladas de bombas se lanzaron en la campaña aérea?",
          "respuesta": "88.500 toneladas"
        },
        {
          "pregunta": "¿Qué evento aéreo apoyó la ofensiva terrestre del 23 de febrero?",
          "respuesta": "Ataques aéreos coordinados"
        },
        {
          "pregunta": "¿Cuál fue el resultado final de la campaña aérea?",
          "respuesta": "Liberación de Kuwait y retirada iraquí"
        },
        {
          "pregunta": "¿Qué tipo de vigilancia fue clave en la guerra?",
          "respuesta": "Vigilancia satelital"
        },
        {
          "pregunta": "¿Qué tipo de avión no tripulado se usó en la guerra?",
          "respuesta": "Drones (aeronaves no tripuladas)"
        },
        {
          "pregunta": "¿Qué tipo de guerra integró operaciones aéreas, terrestres y marítimas?",
          "respuesta": "Guerra multidimensional"
        },
        {
          "pregunta": "¿Qué tipo de maniobras usó la coalición para evitar enfrentamientos directos?",
          "respuesta": "Tácticas de maniobra"
        },
        {
          "pregunta": "¿Qué país europeo de habla hispana participó en la coalición?",
          "respuesta": "España"
        },
        {
          "pregunta": "¿Qué tipo de buques lanzaron misiles en la campaña del Golfo?",
          "respuesta": "Buques de guerra"
        },
        {
          "pregunta": "¿Qué tipo de fuerzas participaron junto a submarinos y aviación en poder naval?",
          "respuesta": "Infantería de marina"
        }
      ]
      

